{"game_round":1,"participant_id":"Participant1","content":"```json\n{\n  \"expectation\": 4,\n  \"reason\": \"根据网络边际收益（0.75），预计会有超过一半的人参与，考虑到每个人的独立收益分布（1-6），我会选择在参与人数接近中间值时加入，即4人。\"\n}\n```","expectation":4,"reason":"根据网络边际收益（0.75），预计会有超过一半的人参与，考虑到每个人的独立收益分布（1-6），我会选择在参与人数接近中间值时加入，即4人。"}
{"game_round":1,"participant_id":"Participant2","content":"```json\n{\n  \"expectation\": 3,\n  \"reason\": \"根据网络边际收益（network benefit）为0.75的信息，可以推断出总共有约75%的概率会有更多人参与。由于我是一个独立收益为2的参与者，且在预期中有更多的参与者时，我的效用可能会增加，因此我会考虑加入。\"\n}\n```","expectation":3,"reason":"根据网络边际收益（network benefit）为0.75的信息，可以推断出总共有约75%的概率会有更多人参与。由于我是一个独立收益为2的参与者，且在预期中有更多的参与者时，我的效用可能会增加，因此我会考虑加入。"}
{"game_round":1,"participant_id":"Participant3","content":"```json\n{\n    \"expectation\": 4,\n    \"reason\": \"根据网络效应（network effect）为0.75，我们可以预期会有大约75%的人参加。考虑到我的个人价值为3，我会计算我的期望效用，并选择是否参加。\"\n}\n```","expectation":4,"reason":"根据网络效应（network effect）为0.75，我们可以预期会有大约75%的人参加。考虑到我的个人价值为3，我会计算我的期望效用，并选择是否参加。"}
{"game_round":1,"participant_id":"Participant4","content":"```json\n{\n    \"expectation\": 3,\n    \"reason\": \"根据网络边际收益（network benefit）为0.75，以及每个参与者独立收益（standalone value）的分布，我预计会有3个人参与。\"\n}\n```","expectation":3,"reason":"根据网络边际收益（network benefit）为0.75，以及每个参与者独立收益（standalone value）的分布，我预计会有3个人参与。"}
{"game_round":1,"participant_id":"Participant5","content":"```json\n{\n  \"expectation\": 5,\n  \"reason\": \"根据网络效应，我预计会有5人参加。由于每个人的standalone_value不同，他们可能会基于这个信息来调整他们的决策。\"\n}\n```","expectation":5,"reason":"根据网络效应，我预计会有5人参加。由于每个人的standalone_value不同，他们可能会基于这个信息来调整他们的决策。"}
{"game_round":1,"participant_id":"Participant6","content":"```json\n{\n    \"expectation\": 3,\n    \"reason\": \"根据网络边际收益（network benefit）为0.75的信息，我预计会有大约75%的人参与。考虑到每个人的独立收益（standalone value）分布在1到6之间，我可以合理地推断出至少有3个人会参与，因为他们可能具有较高的独立收益。\"\n}\n```","expectation":3,"reason":"根据网络边际收益（network benefit）为0.75的信息，我预计会有大约75%的人参与。考虑到每个人的独立收益（standalone value）分布在1到6之间，我可以合理地推断出至少有3个人会参与，因为他们可能具有较高的独立收益。"}
{"game_round":2,"participant_id":"Participant1","content":"```json\n{\n  \"expectation\": 4,\n  \"reason\": \"根据实际参与人数（4）和网络边际收益（0.75），我预期会有超过一半的人参与。由于每个人独立收益的分布（1-6），我选择了在参与人数接近中间值时加入，即4人。\"\n}\n```","expectation":4,"reason":"根据实际参与人数（4）和网络边际收益（0.75），我预期会有超过一半的人参与。由于每个人独立收益的分布（1-6），我选择了在参与人数接近中间值时加入，即4人。"}
{"game_round":2,"participant_id":"Participant2","content":"```json\n{\n  \"expectation\": 4,\n  \"reason\": \"基于上一轮的实际参与人数为4，以及网络边际收益为0.75的信息，我可以合理推测未来可能有更多人参与。虽然我的独立收益为2，但我认为如果其他人也预计到这个可能性，他们也会参与进来。因此，我会选择参加。\"\n}\n```","expectation":4,"reason":"基于上一轮的实际参与人数为4，以及网络边际收益为0.75的信息，我可以合理推测未来可能有更多人参与。虽然我的独立收益为2，但我认为如果其他人也预计到这个可能性，他们也会参与进来。因此，我会选择参加。"}
{"game_round":2,"participant_id":"Participant3","content":"```json\n{\n    \"expectation\": 4,\n    \"reason\": \"在实际发生的会议上，我们得知有4人参与了。由于每个人的预期效用都基于网络效应，我也会将这个信息纳入考虑，继续预期可能的参与人数。\"\n}\n```","expectation":4,"reason":"在实际发生的会议上，我们得知有4人参与了。由于每个人的预期效用都基于网络效应，我也会将这个信息纳入考虑，继续预期可能的参与人数。"}
{"game_round":2,"participant_id":"Participant4","content":"```json\n{\n    \"expectation\": 3,\n    \"reason\": \"在上一轮中，实际参与的人数为4，这超出了我的预期。虽然网络边际收益为0.75，但我认为可能是因为某些特定因素影响了实际参与率，比如随机性或特殊情况导致的实际参与人数超过了预期。\"\n}\n```","expectation":3,"reason":"在上一轮中，实际参与的人数为4，这超出了我的预期。虽然网络边际收益为0.75，但我认为可能是因为某些特定因素影响了实际参与率，比如随机性或特殊情况导致的实际参与人数超过了预期。"}
{"game_round":2,"participant_id":"Participant5","content":"```json\n{\n  \"expectation\": 4,\n  \"reason\": \"根据实际参与人数，我更新了对下一轮的期望。虽然实际人数低于预期，但我仍然认为还有可能有更多人参加，尤其是在考虑到网络效应的情况下。\"\n}\n```","expectation":4,"reason":"根据实际参与人数，我更新了对下一轮的期望。虽然实际人数低于预期，但我仍然认为还有可能有更多人参加，尤其是在考虑到网络效应的情况下。"}
{"game_round":2,"participant_id":"Participant6","content":"```json\n{\n    \"expectation\": 3,\n    \"reason\": \"根据网络边际收益为0.75的信息，我估计会有大约75%的人参与。由于实际参与人数为4，这表明有2人没有参与，可能是因为他们的独立收益较低或者他们对参与的积极性不高。基于这个信息，我认为有3个人应该会参与。\"\n}\n```","expectation":3,"reason":"根据网络边际收益为0.75的信息，我估计会有大约75%的人参与。由于实际参与人数为4，这表明有2人没有参与，可能是因为他们的独立收益较低或者他们对参与的积极性不高。基于这个信息，我认为有3个人应该会参与。"}
{"game_round":3,"participant_id":"Participant1","content":"```json\n{\n  \"expectation\": 5,\n  \"reason\": \"根据实际参与人数（5）和网络边际收益（0.75），我预期会有超过半数的人参与。考虑到每个人的独立收益分布（1-6），我选择了在参与人数接近中间值时加入，即5人。\"\n}\n```","expectation":5,"reason":"根据实际参与人数（5）和网络边际收益（0.75），我预期会有超过半数的人参与。考虑到每个人的独立收益分布（1-6），我选择了在参与人数接近中间值时加入，即5人。"}
{"game_round":3,"participant_id":"Participant2","content":"```json\n{\n  \"expectation\": 5,\n  \"reason\": \"根据上一轮的实际参与人数为5，以及网络边际收益为0.75的信息，我认为在未来可能会有更多的参与者。尽管我的独立收益为2，但由于其他参与者可能已经预见到了这种趋势，并且增加了他们的参与概率，所以我也会考虑加入。\"\n}\n```","expectation":5,"reason":"根据上一轮的实际参与人数为5，以及网络边际收益为0.75的信息，我认为在未来可能会有更多的参与者。尽管我的独立收益为2，但由于其他参与者可能已经预见到了这种趋势，并且增加了他们的参与概率，所以我也会考虑加入。"}
{"game_round":3,"participant_id":"Participant3","content":"```json\n{\n    \"expectation\": 5,\n    \"reason\": \"在实际发生的会议上，我们得知有5人参与了。虽然网络效应为0.75，但我仍会继续调整我的预期，因为实际参与人数已经高于预期。\"\n}\n```","expectation":5,"reason":"在实际发生的会议上，我们得知有5人参与了。虽然网络效应为0.75，但我仍会继续调整我的预期，因为实际参与人数已经高于预期。"}
{"game_round":3,"participant_id":"Participant4","content":"```json\n{\n    \"expectation\": 4,\n    \"reason\": \"在上一轮中，实际参与的人数为5，这再次超出了我的预期。虽然网络边际收益为0.75，但我认为可能是由于某种特殊原因导致的实际参与人数超过了预期。\"\n}\n```","expectation":4,"reason":"在上一轮中，实际参与的人数为5，这再次超出了我的预期。虽然网络边际收益为0.75，但我认为可能是由于某种特殊原因导致的实际参与人数超过了预期。"}
{"game_round":3,"participant_id":"Participant5","content":"```json\n{\n  \"expectation\": 5,\n  \"reason\": \"根据实际参与人数，我再次确认了我的预期。尽管实际人数超过了预期，但网络效应仍可能导致更多人加入。\"\n}\n```","expectation":5,"reason":"根据实际参与人数，我再次确认了我的预期。尽管实际人数超过了预期，但网络效应仍可能导致更多人加入。"}
{"game_round":3,"participant_id":"Participant6","content":"```json\n{\n    \"expectation\": 3,\n    \"reason\": \"根据网络边际收益为0.75的信息，我估计会有大约75%的人参与。由于实际参与人数为5，这意味着有2人没有参与。这种情况可能是由于某些因素导致的低参与率，比如认知偏差、资源分配不均或心理压力等。鉴于此，我认为有3个人应该会参与。\"\n}\n```","expectation":3,"reason":"根据网络边际收益为0.75的信息，我估计会有大约75%的人参与。由于实际参与人数为5，这意味着有2人没有参与。这种情况可能是由于某些因素导致的低参与率，比如认知偏差、资源分配不均或心理压力等。鉴于此，我认为有3个人应该会参与。"}
{"game_round":4,"participant_id":"Participant1","content":"```json\n{\n  \"expectation\": 5,\n  \"reason\": \"根据实际参与人数（5）和网络边际收益（0.75），我预期会有超过半数的人参与。考虑到每个人的独立收益分布（1-6），我选择了在参与人数接近中间值时加入，即5人。\"\n}\n```","expectation":5,"reason":"根据实际参与人数（5）和网络边际收益（0.75），我预期会有超过半数的人参与。考虑到每个人的独立收益分布（1-6），我选择了在参与人数接近中间值时加入，即5人。"}
{"game_round":4,"participant_id":"Participant2","content":"```json\n{\n  \"expectation\": 5,\n  \"reason\": \"根据上一轮的实际参与人数为5，以及网络边际收益为0.75的信息，我认为在未来可能会有更多的参与者。虽然我的独立收益为2，但由于其他参与者可能已经预见到了这种趋势，并且增加了他们的参与概率，所以我也会考虑加入。\"\n}\n```","expectation":5,"reason":"根据上一轮的实际参与人数为5，以及网络边际收益为0.75的信息，我认为在未来可能会有更多的参与者。虽然我的独立收益为2，但由于其他参与者可能已经预见到了这种趋势，并且增加了他们的参与概率，所以我也会考虑加入。"}
{"game_round":4,"participant_id":"Participant3","content":"```json\n{\n    \"expectation\": 5,\n    \"reason\": \"在实际发生的会议上，我们得知有5人参与了。尽管网络效应为0.75，但实际参与人数已经达到预期的最大值，所以我将继续保持我的预期不变。\"\n}\n```","expectation":5,"reason":"在实际发生的会议上，我们得知有5人参与了。尽管网络效应为0.75，但实际参与人数已经达到预期的最大值，所以我将继续保持我的预期不变。"}
{"game_round":4,"participant_id":"Participant4","content":"```json\n{\n    \"expectation\": 4,\n    \"reason\": \"在上一轮中，实际参与的人数为5，这超出了我的预期。虽然网络边际收益为0.75，但我认为可能是因为某些特定因素影响了实际参与率，比如随机性或特殊情况导致的实际参与人数超过了预期。\"\n}\n```","expectation":4,"reason":"在上一轮中，实际参与的人数为5，这超出了我的预期。虽然网络边际收益为0.75，但我认为可能是因为某些特定因素影响了实际参与率，比如随机性或特殊情况导致的实际参与人数超过了预期。"}
{"game_round":4,"participant_id":"Participant5","content":"```json\n{\n  \"expectation\": 5,\n  \"reason\": \"根据实际参与人数，我保持我的预期不变。在网络效应的影响下，即使实际人数接近或超过预期，仍有其他人可能继续参与。\"\n}\n```","expectation":5,"reason":"根据实际参与人数，我保持我的预期不变。在网络效应的影响下，即使实际人数接近或超过预期，仍有其他人可能继续参与。"}
{"game_round":4,"participant_id":"Participant6","content":"```json\n{\n    \"expectation\": 3,\n    \"reason\": \"根据网络边际收益为0.75的信息，我估计会有大约75%的人参与。由于实际参与人数为5，这意味着有2人没有参与。这种情况可能是由于某些因素导致的低参与率，比如认知偏差、资源分配不均或心理压力等。鉴于此，我认为有3个人应该会参与。\"\n}\n```","expectation":3,"reason":"根据网络边际收益为0.75的信息，我估计会有大约75%的人参与。由于实际参与人数为5，这意味着有2人没有参与。这种情况可能是由于某些因素导致的低参与率，比如认知偏差、资源分配不均或心理压力等。鉴于此，我认为有3个人应该会参与。"}
{"game_round":5,"participant_id":"Participant1","content":"```json\n{\n  \"expectation\": 5,\n  \"reason\": \"根据实际参与人数（5）和网络边际收益（0.75），我预期会有超过半数的人参与。考虑到每个人的独立收益分布（1-6），我选择了在参与人数接近中间值时加入，即5人。\"\n}\n```","expectation":5,"reason":"根据实际参与人数（5）和网络边际收益（0.75），我预期会有超过半数的人参与。考虑到每个人的独立收益分布（1-6），我选择了在参与人数接近中间值时加入，即5人。"}
{"game_round":5,"participant_id":"Participant2","content":"```json\n{\n  \"expectation\": 5,\n  \"reason\": \"根据上一轮的实际参与人数为5，以及网络边际收益为0.75的信息，我认为在未来可能会有更多的参与者。虽然我的独立收益为2，但由于其他参与者可能已经预见到了这种趋势，并且增加了他们的参与概率，所以我也会考虑加入。\"\n}\n```","expectation":5,"reason":"根据上一轮的实际参与人数为5，以及网络边际收益为0.75的信息，我认为在未来可能会有更多的参与者。虽然我的独立收益为2，但由于其他参与者可能已经预见到了这种趋势，并且增加了他们的参与概率，所以我也会考虑加入。"}
{"game_round":5,"participant_id":"Participant3","content":"```json\n{\n    \"expectation\": 5,\n    \"reason\": \"在实际发生的会议上，我们得知有5人参与了。虽然网络效应为0.75，但我们发现实际参与人数已经达到了预期的最大值，因此我将继续保持我的预期不变。\"\n}\n```","expectation":5,"reason":"在实际发生的会议上，我们得知有5人参与了。虽然网络效应为0.75，但我们发现实际参与人数已经达到了预期的最大值，因此我将继续保持我的预期不变。"}
{"game_round":5,"participant_id":"Participant4","content":"```json\n{\n    \"expectation\": 4,\n    \"reason\": \"在上一轮中，实际参与的人数为5，这再次超出了我的预期。虽然网络边际收益为0.75，但我认为可能是由于某种特殊原因导致的实际参与人数超过了预期。\"\n}\n```","expectation":4,"reason":"在上一轮中，实际参与的人数为5，这再次超出了我的预期。虽然网络边际收益为0.75，但我认为可能是由于某种特殊原因导致的实际参与人数超过了预期。"}
{"game_round":5,"participant_id":"Participant5","content":"```json\n{\n  \"expectation\": 5,\n  \"reason\": \"根据实际参与人数，我再次确认了我的预期。在网络效应的影响下，即使实际人数接近或超过预期，仍有其他人可能继续参与。\"\n}\n```","expectation":5,"reason":"根据实际参与人数，我再次确认了我的预期。在网络效应的影响下，即使实际人数接近或超过预期，仍有其他人可能继续参与。"}
{"game_round":5,"participant_id":"Participant6","content":"```json\n{\n    \"expectation\": 3,\n    \"reason\": \"根据网络边际收益为0.75的信息，我估计会有大约75%的人参与。由于实际参与人数为5，这意味着有2人没有参与。这种情况可能是由于某些因素导致的低参与率，比如认知偏差、资源分配不均或心理压力等。鉴于此，我认为有3个人应该会参与。\"\n}\n```","expectation":3,"reason":"根据网络边际收益为0.75的信息，我估计会有大约75%的人参与。由于实际参与人数为5，这意味着有2人没有参与。这种情况可能是由于某些因素导致的低参与率，比如认知偏差、资源分配不均或心理压力等。鉴于此，我认为有3个人应该会参与。"}
{"game_round":6,"participant_id":"Participant1","content":"```json\n{\n  \"expectation\": 5,\n  \"reason\": \"根据实际参与人数（5）和网络边际收益（0.75），我预期会有超过半数的人参与。考虑到每个人的独立收益分布（1-6），我选择了在参与人数接近中间值时加入，即5人。\"\n}\n```","expectation":5,"reason":"根据实际参与人数（5）和网络边际收益（0.75），我预期会有超过半数的人参与。考虑到每个人的独立收益分布（1-6），我选择了在参与人数接近中间值时加入，即5人。"}
{"game_round":6,"participant_id":"Participant2","content":"```json\n{\n  \"expectation\": 5,\n  \"reason\": \"根据上一轮的实际参与人数为5，以及网络边际收益为0.75的信息，我认为在未来可能会有更多的参与者。虽然我的独立收益为2，但由于其他参与者可能已经预见到了这种趋势，并且增加了他们的参与概率，所以我也会考虑加入。\"\n}\n```","expectation":5,"reason":"根据上一轮的实际参与人数为5，以及网络边际收益为0.75的信息，我认为在未来可能会有更多的参与者。虽然我的独立收益为2，但由于其他参与者可能已经预见到了这种趋势，并且增加了他们的参与概率，所以我也会考虑加入。"}
{"game_round":6,"participant_id":"Participant3","content":"```json\n{\n    \"expectation\": 5,\n    \"reason\": \"在实际发生的会议上，我们得知有5人参与了。虽然网络效应为0.75，但我们发现实际参与人数已经达到了预期的最大值，因此我将继续保持我的预期不变。\"\n}\n```","expectation":5,"reason":"在实际发生的会议上，我们得知有5人参与了。虽然网络效应为0.75，但我们发现实际参与人数已经达到了预期的最大值，因此我将继续保持我的预期不变。"}
{"game_round":6,"participant_id":"Participant4","content":"```json\n{\n    \"expectation\": 4,\n    \"reason\": \"在上一轮中，实际参与的人数为5，这超出了我的预期。虽然网络边际收益为0.75，但我认为可能是因为某些特定因素影响了实际参与率，比如随机性或特殊情况导致的实际参与人数超过了预期。\"\n}\n```","expectation":4,"reason":"在上一轮中，实际参与的人数为5，这超出了我的预期。虽然网络边际收益为0.75，但我认为可能是因为某些特定因素影响了实际参与率，比如随机性或特殊情况导致的实际参与人数超过了预期。"}
{"game_round":6,"participant_id":"Participant5","content":"```json\n{\n  \"expectation\": 5,\n  \"reason\": \"根据实际参与人数，我保持我的预期不变。在网络效应的影响下，即使实际人数接近或超过预期，仍有其他人可能继续参与。\"\n}\n```","expectation":5,"reason":"根据实际参与人数，我保持我的预期不变。在网络效应的影响下，即使实际人数接近或超过预期，仍有其他人可能继续参与。"}
{"game_round":6,"participant_id":"Participant6","content":"```json\n{\n    \"expectation\": 3,\n    \"reason\": \"根据网络边际收益为0.75的信息，我估计会有大约75%的人参与。由于实际参与人数为5，这意味着有2人没有参与。这种情况可能是由于某些因素导致的低参与率，比如认知偏差、资源分配不均或心理压力等。鉴于此，我认为有3个人应该会参与。\"\n}\n```","expectation":3,"reason":"根据网络边际收益为0.75的信息，我估计会有大约75%的人参与。由于实际参与人数为5，这意味着有2人没有参与。这种情况可能是由于某些因素导致的低参与率，比如认知偏差、资源分配不均或心理压力等。鉴于此，我认为有3个人应该会参与。"}
