{"game_round":1,"participant_id":"Participant1","content":"```json\n{\n  \"expectation\": 3,\n  \"reason\": \"根据网络边际收益（0.25）和每个人的单独收益（1），我预计会有大约3人参与。\"\n}\n```","expectation":3,"reason":"根据网络边际收益（0.25）和每个人的单独收益（1），我预计会有大约3人参与。"}
{"game_round":1,"participant_id":"Participant2","content":"```json\n{\n  \"expectation\": 2,\n  \"reason\": \"根据网络效应假设，每个人的期望参与人数应该接近平均值。在给定的分布下，每个参与者独立收益为1到6，网络边际收益为0.25。为了最大化效用，每个人都应该预期其他人也会参与，因此我预计会有大约3-4人参与。\"\n}\n```","expectation":2,"reason":"根据网络效应假设，每个人的期望参与人数应该接近平均值。在给定的分布下，每个参与者独立收益为1到6，网络边际收益为0.25。为了最大化效用，每个人都应该预期其他人也会参与，因此我预计会有大约3-4人参与。"}
{"game_round":1,"participant_id":"Participant3","content":"```json\n{\n  \"expectation\": 3,\n  \"reason\": \"根据网络效应和每个人的独立收益，我预计会有3人参加，因为我个人的价值（3）加上可能的2-4人网络边际收益（总共0.75），减去基础费用，总效用应该在正区间内，因此我会考虑加入讨论。\"\n}\n```","expectation":3,"reason":"根据网络效应和每个人的独立收益，我预计会有3人参加，因为我个人的价值（3）加上可能的2-4人网络边际收益（总共0.75），减去基础费用，总效用应该在正区间内，因此我会考虑加入讨论。"}
{"game_round":1,"participant_id":"Participant4","content":"```json\n{\n    \"expectation\": 3,\n    \"reason\": \"根据网络效应，如果参与人数少于6人，则每个人的实际收益都会减少。为了最大化收益，我预计会有3-4人参加。\"\n}\n```","expectation":3,"reason":"根据网络效应，如果参与人数少于6人，则每个人的实际收益都会减少。为了最大化收益，我预计会有3-4人参加。"}
{"game_round":1,"participant_id":"Participant5","content":"```json\n{\n  \"expectation\": 4,\n  \"reason\": \"根据网络边际收益（0.25）和我的单独价值（5），我预计会有超过一半的人参与，即超过3人。\"\n}\n```","expectation":4,"reason":"根据网络边际收益（0.25）和我的单独价值（5），我预计会有超过一半的人参与，即超过3人。"}
{"game_round":1,"participant_id":"Participant6","content":"```json\n{\n  \"expectation\": 3,\n  \"reason\": \"根据网络边际收益（0.25）和每个人的独立收益（1到6），我预计会有大约3个人参加。\"\n}\n```","expectation":3,"reason":"根据网络边际收益（0.25）和每个人的独立收益（1到6），我预计会有大约3个人参加。"}
