{"game_round":1,"participant_id":"Participant1","content":"```json\n{\n    \"expectation\": 3,\n    \"reason\": \"根据网络边际收益（network_effect）为0.25的信息，以及所有人的standalone_value为[1, 2, 3, 4, 5, 6]的分布，我预计会有大约一半的人参与。\"\n}\n```","expectation":3,"reason":"根据网络边际收益（network_effect）为0.25的信息，以及所有人的standalone_value为[1, 2, 3, 4, 5, 6]的分布，我预计会有大约一半的人参与。"}
{"game_round":1,"participant_id":"Participant2","content":"```json\n{\n    \"expectation\": 2,\n    \"reason\": \"根据网络边际收益（0.25）和我的单独价值（2），我预期至少会有2人参加。\"\n}\n```","expectation":2,"reason":"根据网络边际收益（0.25）和我的单独价值（2），我预期至少会有2人参加。"}
{"game_round":1,"participant_id":"Participant3","content":"```json\n{\n  \"expectation\": 3,\n  \"reason\": \"根据网络效应，假设所有人都会有同样的参与意愿，那么每个人都会期望其他人也会加入，这会导致总参与人数增加。\"\n}\n```","expectation":3,"reason":"根据网络效应，假设所有人都会有同样的参与意愿，那么每个人都会期望其他人也会加入，这会导致总参与人数增加。"}
{"game_round":1,"participant_id":"Participant4","content":"```json\n{\n    \"expectation\": 3,\n    \"reason\": \"根据网络边际收益（0.25）和我自身的独立收益（4），我认为总参与人数会接近于平均值加上这个边际收益。\"\n}\n```","expectation":3,"reason":"根据网络边际收益（0.25）和我自身的独立收益（4），我认为总参与人数会接近于平均值加上这个边际收益。"}
{"game_round":1,"participant_id":"Participant5","content":"```json\n{\n    \"expectation\": 3,\n    \"reason\": \"根据网络边际收益（0.25），我预计会有大约一半的人参与。我的单独价值是5，所以我认为我会考虑参加。\"\n}\n```","expectation":3,"reason":"根据网络边际收益（0.25），我预计会有大约一半的人参与。我的单独价值是5，所以我认为我会考虑参加。"}
{"game_round":1,"participant_id":"Participant6","content":"```json\n{\n  \"expectation\": 4,\n  \"reason\": \"根据网络边际收益（network_benefit）为0.25的信息，我们可以推测每个人的效用在平均值附近波动。由于每个人独立收益（standalone_value）从1到6不等，我们可以通过平均值来估计总体效果。考虑到每个参与者可能受到其他参与者影响的程度，我预计会有大约一半的人会参加，即4人。\"\n}\n```","expectation":4,"reason":"根据网络边际收益（network_benefit）为0.25的信息，我们可以推测每个人的效用在平均值附近波动。由于每个人独立收益（standalone_value）从1到6不等，我们可以通过平均值来估计总体效果。考虑到每个参与者可能受到其他参与者影响的程度，我预计会有大约一半的人会参加，即4人。"}
